README.txt
setup.py
ckanext/__init__.py
ckanext/amqp.py
ckanext/api_command.py
ckanext/command.py
ckanext/link_checker.py
ckanext/loader.py
ckanext.egg-info/PKG-INFO
ckanext.egg-info/SOURCES.txt
ckanext.egg-info/dependency_links.txt
ckanext.egg-info/entry_points.txt
ckanext.egg-info/requires.txt
ckanext.egg-info/top_level.txt
ckanext/geo/__init__.py
ckanext/geo/geo_form.py
ckanext/iso19139/__init__.py
ckanext/iso19139/loader.py
ckanext/iso19139/reader.py
ckanext/plugins/__init__.py
ckanext/plugins/form_api_tester.py
ckanext/tests/__init__.py
ckanext/tests/test_loader.py
ckanext/tests/plugins/__init__.py
ckanext/tests/plugins/test_form_api_tester.py