Metadata-Version: 1.0
Name: ckanext
Version: 0.1
Summary: CKAN common library for extensions
Home-page: http://ckan.org/
Author: Open Knowledge Foundation
Author-email: info@okfn.org
License: AGPL
Keywords: data packaging component tool server
Platform: UNKNOWN
